MANIFEST.in
README.md
setup.cfg
setup.py
control_and_supervised_learning/__init__.py
control_and_supervised_learning/eval.py
control_and_supervised_learning/model_20000.pt
control_and_supervised_learning/policy.py
smarts_agent_casl.egg-info/PKG-INFO
smarts_agent_casl.egg-info/SOURCES.txt
smarts_agent_casl.egg-info/dependency_links.txt
smarts_agent_casl.egg-info/requires.txt
smarts_agent_casl.egg-info/top_level.txt
smarts_agent_casl.egg-info/zip-safe